timetracking/__init__.py
timetracking/database.py
timetracking/email_export.py
timetracking/gui.py
timetracking/main.py
timetracking/password_utils.py
timetracking/pdf_export.py
timetracking-1.0.51.dist-info/licenses/LICENSE
timetracking-1.0.51.dist-info/METADATA
timetracking-1.0.51.dist-info/WHEEL
timetracking-1.0.51.dist-info/entry_points.txt
timetracking-1.0.51.dist-info/top_level.txt
timetracking-1.0.51.dist-info/RECORD
