Metadata-Version: 2.4
Name: timetracking
Version: 1.0.51
Summary: A Python time tracking application with GUI, PDF export, and email functionality
Home-page: https://github.com/ricardo-nolan/timetracking
Author: Ricardo Nolan
Author-email: Ricardo Nolan <ricardo@example.com>
Maintainer-email: Ricardo Nolan <ricardo@example.com>
License: MIT
Project-URL: Homepage, https://github.com/ricardo-nolan/timetracking
Project-URL: Repository, https://github.com/ricardo-nolan/timetracking
Project-URL: Issues, https://github.com/ricardo-nolan/timetracking/issues
Keywords: time tracking,productivity,gui,pdf,email,sqlite
Classifier: Development Status :: 4 - Beta
Classifier: Intended Audience :: End Users/Desktop
Classifier: License :: OSI Approved :: MIT License
Classifier: Operating System :: OS Independent
Classifier: Programming Language :: Python :: 3
Classifier: Programming Language :: Python :: 3.7
Classifier: Programming Language :: Python :: 3.8
Classifier: Programming Language :: Python :: 3.9
Classifier: Programming Language :: Python :: 3.10
Classifier: Programming Language :: Python :: 3.11
Classifier: Programming Language :: Python :: 3.12
Classifier: Programming Language :: Python :: 3.13
Classifier: Topic :: Office/Business
Classifier: Topic :: Utilities
Requires-Python: >=3.7
License-File: LICENSE
Requires-Dist: reportlab==4.0.4
Requires-Dist: Pillow
Requires-Dist: pytest
Requires-Dist: pytest-cov
Requires-Dist: cryptography
Requires-Dist: requests
Dynamic: author
Dynamic: home-page
Dynamic: license-file
Dynamic: requires-python
